phenofit/__init__.py
phenofit/api_opl.cp312-win_amd64.pyd
phenofit/func_opl.py
phenofit-0.0.7.dist-info/LICENSE
phenofit-0.0.7.dist-info/METADATA
phenofit-0.0.7.dist-info/WHEEL
phenofit-0.0.7.dist-info/top_level.txt
phenofit-0.0.7.dist-info/RECORD
