Metadata-Version: 2.1
Name: phenofit
Version: 0.0.7
Summary: A small package for phenology analysis
Home-page: https://github.com/spjace/phenofit
Author: Shen Pengju
Author-email: spjace@sina.com
Classifier: Programming Language :: Python :: 3
Classifier: License :: OSI Approved :: MIT License
Classifier: Operating System :: OS Independent
Requires-Python: >=3.7
License-File: LICENSE
